Workbook

Sheet Dashboard
B2: 🏢 ELITE APARTMENT MANAGEMENT — DASHBOARD 2026
B4: UNITS OCCUPIED | F4: UNITS VACANT | J4: OCCUPANCY RATE | N4: TOTAL RENT/MONTH
B6: =COUNTIF('Rent Tracker'!B3:B32,"<>VACANT") -> 20 | F6: =COUNTIF('Rent Tracker'!B3:B32,"VACANT") -> 10 | J6: =IFERROR(COUNTIF('Rent Tracker'!B3:B32,"<>VACANT")/COUNTIF('Rent Tracker'!A3:A32,"<>"),0) -> 1.4285714 | N6: =SUM('Rent Tracker'!F3:F32) -> 31000
B9: COLLECTED (MAR) | F9: TOTAL ARREARS | J9: EXPENSES YTD | N9: NET INCOME YTD
B11: ='Rent Tracker'!N34 -> 7000 | F11: =SUMIF(Arrears!H3:H32,">0",Arrears!H3:H32) -> 51000 | J11: =Expenses!P23 -> 9000 | N11: ='Rent Tracker'!AI34-Expenses!P23 -> 313000
B14: TOP DEBTORS — Who Owes Most
B15: House | C15: Tenant | D15: Rent/Mo | E15: Jan Bal | F15: Feb Bal | G15: Mar Bal | H15: Paid YTD | I15: Still Owes | J15: Months Behind | K15: Status
B16: =Arrears!A3 -> House 1 | C16: =Arrears!B3 -> IAN | D16: =Arrears!C3 -> 7000 | E16: =Arrears!D3 -> 0 | F16: =Arrears!E3 -> 0 | G16: =Arrears!F3 -> 0 | H16: =Arrears!G3 -> 84000 | I16: =Arrears!H3 -> 0 | J16: =Arrears!I3 -> 0 | K16: =Arrears!L3 -> Legal
B17: =Arrears!A4 -> House 2 | C17: =Arrears!B4 -> JAMES | D17: =Arrears!C4 -> 8000 | E17: =Arrears!D4 -> -42000 | F17: =Arrears!E4 -> -34000 | G17: =Arrears!F4 -> -26000 | H17: =Arrears!G4 -> 96000 | I17: =Arrears!H4 -> 0 | J17: =Arrears!I4 -> 0 | K17: =Arrears!L4 -> Legal
B18: =Arrears!A5 -> House 3 | C18: =Arrears!B5 -> KELVIN | D18: =Arrears!C5 -> 8000 | E18: =Arrears!D5 -> -24000 | F18: =Arrears!E5 -> -16000 | G18: =Arrears!F5 -> -8000 | H18: =Arrears!G5 -> 45000 | I18: =Arrears!H5 -> 51000 | J18: =Arrears!I5 -> 7 | K18: =Arrears!L5 -> Notice Issued
B19: =Arrears!A6 -> House 4 | C19: =Arrears!B6 -> JOHN | D19: =Arrears!C6 -> 8000 | E19: =Arrears!D6 -> -82000 | F19: =Arrears!E6 -> -74000 | G19: =Arrears!F6 -> -66000 | H19: =Arrears!G6 -> 97000 | I19: =Arrears!H6 -> -1000 | J19: =Arrears!I6 -> 0 | K19: =Arrears!L6 -> Pending
B20: =Arrears!A7 -> House 5 | C20: =Arrears!B7 -> VACANT | D20: =Arrears!C7 -> 0 | E20: =Arrears!D7 | F20: =Arrears!E7 | G20: =Arrears!F7 | H20: =Arrears!G7 | I20: =Arrears!H7 | J20: =Arrears!I7 | K20: =Arrears!L7 -> 0
B21: =Arrears!A8 -> House 6 | C21: =Arrears!B8 -> VACANT | D21: =Arrears!C8 -> 0 | E21: =Arrears!D8 | F21: =Arrears!E8 | G21: =Arrears!F8 | H21: =Arrears!G8 | I21: =Arrears!H8 | J21: =Arrears!I8 | K21: =Arrears!L8 -> 0
B22: =Arrears!A9 -> House 7 | C22: =Arrears!B9 -> VACANT | D22: =Arrears!C9 -> 0 | E22: =Arrears!D9 | F22: =Arrears!E9 | G22: =Arrears!F9 | H22: =Arrears!G9 | I22: =Arrears!H9 | J22: =Arrears!I9 | K22: =Arrears!L9 -> 0
B23: =Arrears!A10 -> House 8 | C23: =Arrears!B10 -> VACANT | D23: =Arrears!C10 -> 0 | E23: =Arrears!D10 | F23: =Arrears!E10 | G23: =Arrears!F10 | H23: =Arrears!G10 | I23: =Arrears!H10 | J23: =Arrears!I10 | K23: =Arrears!L10 -> 0
B24: =Arrears!A11 -> House 9 | C24: =Arrears!B11 -> VACANT | D24: =Arrears!C11 -> 0 | E24: =Arrears!D11 -> 0 | F24: =Arrears!E11 -> 0 | G24: =Arrears!F11 -> 0 | H24: =Arrears!G11 -> 0 | I24: =Arrears!H11 -> 0 | J24: =Arrears!I11 | K24: =Arrears!L11 -> 0
B25: =Arrears!A12 -> House 10 | C25: =Arrears!B12 -> VACANT | D25: =Arrears!C12 -> 0 | E25: =Arrears!D12 | F25: =Arrears!E12 | G25: =Arrears!F12 | H25: =Arrears!G12 | I25: =Arrears!H12 | J25: =Arrears!I12 | K25: =Arrears!L12 -> 0
B28: HOW TO USE: Go to 'Rent Tracker' → type amount paid in BLUE columns each month. Arrears, P&L and Dashboard update automatically. Blue = type here. Everything else = auto.
B32: Month | C32: Collected | D32: Expected | E32: Expenses | F32: Net
B33: Jan | C33: ='Rent Tracker'!J34 -> 179000 | D33: =SUM('Rent Tracker'!F3:F32) -> 31000 | E33: =Expenses!D23 -> 9000 | F33: =C33-E33 -> 170000
B34: Feb | C34: ='Rent Tracker'!L34 -> 7000 | D34: =SUM('Rent Tracker'!F3:F32) -> 31000 | E34: =Expenses!E23 -> 0 | F34: =C34-E34 -> 7000
B35: Mar | C35: ='Rent Tracker'!N34 -> 7000 | D35: =SUM('Rent Tracker'!F3:F32) -> 31000 | E35: =Expenses!F23 -> 0 | F35: =C35-E35 -> 7000
B36: Apr | C36: ='Rent Tracker'!P34 -> 0 | D36: =SUM('Rent Tracker'!F3:F32) -> 31000 | E36: =Expenses!G23 -> 0 | F36: =C36-E36 -> 0
B37: May | C37: ='Rent Tracker'!R34 -> 14000 | D37: =SUM('Rent Tracker'!F3:F32) -> 31000 | E37: =Expenses!H23 -> 0 | F37: =C37-E37 -> 14000
B38: Jun | C38: ='Rent Tracker'!T34 -> 14000 | D38: =SUM('Rent Tracker'!F3:F32) -> 31000 | E38: =Expenses!I23 -> 0 | F38: =C38-E38 -> 14000
B39: Jul | C39: ='Rent Tracker'!V34 -> 26000 | D39: =SUM('Rent Tracker'!F3:F32) -> 31000 | E39: =Expenses!J23 -> 0 | F39: =C39-E39 -> 26000
B40: Aug | C40: ='Rent Tracker'!X34 -> 7000 | D40: =SUM('Rent Tracker'!F3:F32) -> 31000 | E40: =Expenses!K23 -> 0 | F40: =C40-E40 -> 7000
B41: Sep | C41: ='Rent Tracker'!Z34 -> 0 | D41: =SUM('Rent Tracker'!F3:F32) -> 31000 | E41: =Expenses!L23 -> 0 | F41: =C41-E41 -> 0
B42: Oct | C42: ='Rent Tracker'!AB34 -> 19000 | D42: =SUM('Rent Tracker'!F3:F32) -> 31000 | E42: =Expenses!M23 -> 0 | F42: =C42-E42 -> 19000
B43: Nov | C43: ='Rent Tracker'!AD34 -> 14000 | D43: =SUM('Rent Tracker'!F3:F32) -> 31000 | E43: =Expenses!N23 -> 0 | F43: =C43-E43 -> 14000
B44: Dec | C44: ='Rent Tracker'!AF34 -> 35000 | D44: =SUM('Rent Tracker'!F3:F32) -> 31000 | E44: =Expenses!O23 -> 0 | F44: =C44-E44 -> 35000

Sheet Rent Tracker
A1: 🏢 RENT TRACKER 2026 — Type ONLY the amount paid in the BLUE columns. Everything else auto-calculates.
A2: House No. | B2: Tenant Name | C2: Phone | D2: National ID | E2: Type | F2: Rent/Mo (KSh) | G2: Deposit (KSh) | H2: Move-In Date | I2: Lease End | J2: Jan Paid | K2: Jan Bal | L2: Feb Paid | M2: Feb Bal | N2: Mar Paid | O2: Mar Bal | P2: Apr Paid | Q2: Apr Bal | R2: May Paid | S2: May Bal | T2: Jun Paid | U2: Jun Bal | V2: Jul Paid | W2: Jul Bal | X2: Aug Paid | Y2: Aug Bal | Z2: Sep Paid | AA2: Sep Bal | AB2: Oct Paid | AC2: Oct Bal | AD2: Nov Paid | AE2: Nov Bal | AF2: Dec Paid | AG2: Dec Bal | AI2: Total Paid YTD | AJ2: Total Due YTD | AK2: Still Owes | AL2: Status | AM2: Notes
A3: House 1 | B3: IAN | C3: 728031241 | D3: 444 | E3: 1 Bedroom | F3: 7000 | G3: 7000 | J3: 7000 | K3: =IF(F3="","",F3-J3) -> 0 | L3: 7000 | M3: =IF(F3="","",IF(K3="",F3-L3,K3+F3-L3)) -> 0 | N3: 7000 | O3: =IF(F3="","",IF(M3="",F3-N3,M3+F3-N3)) -> 0 | P3: 0 | Q3: =IF(F3="","",IF(O3="",F3-P3,O3+F3-P3)) -> 7000 | R3: 14000 | S3: =IF(F3="","",IF(Q3="",F3-R3,Q3+F3-R3)) -> 0 | T3: 14000 | U3: =IF(F3="","",IF(S3="",F3-T3,S3+F3-T3)) -> -7000 | V3: 0 | W3: =IF(F3="","",IF(U3="",F3-V3,U3+F3-V3)) -> 0 | X3: 7000 | Y3: =IF(F3="","",IF(W3="",F3-X3,W3+F3-X3)) -> 0 | Z3: 0 | AA3: =IF(F3="","",IF(Y3="",F3-Z3,Y3+F3-Z3)) -> 7000 | AB3: 15000 | AC3: =IF(F3="","",IF(AA3="",F3-AB3,AA3+F3-AB3)) -> -1000 | AD3: 6000 | AE3: =IF(F3="","",IF(AC3="",F3-AD3,AC3+F3-AD3)) -> 0 | AF3: 7000 | AG3: =IF(F3="","",IF(AE3="",F3-AF3,AE3+F3-AF3)) -> 0 | AI3: =IF(F3="","",J3+L3+N3+P3+R3+T3+V3+X3+Z3+AB3+AD3+AF3) -> 84000 | AJ3: =IF(F3="","",F3*12) -> 84000 | AK3: =IF(F3="","",AG3) -> 0 | AL3: =IF(F3="","",IF(AK3<=0,"Paid Up",IF(AK3<F3,"Partial","Unpaid"))) -> Paid Up
A4: House 2 | B4: JAMES | C4: 718444018 | D4: 333 | E4: 1 Bedroom | F4: 8000 | G4: 8000 | J4: 50000 | K4: =IF(F4="","",F4-J4) -> -42000 | L4: 0 | M4: =IF(F4="","",IF(K4="",F4-L4,K4+F4-L4)) -> -34000 | N4: 0 | O4: =IF(F4="","",IF(M4="",F4-N4,M4+F4-N4)) -> -26000 | P4: 0 | Q4: =IF(F4="","",IF(O4="",F4-P4,O4+F4-P4)) -> -18000 | R4: 0 | S4: =IF(F4="","",IF(Q4="",F4-R4,Q4+F4-R4)) -> -10000 | T4: 0 | U4: =IF(F4="","",IF(S4="",F4-T4,S4+F4-T4)) -> -2000 | V4: 26000 | W4: =IF(F4="","",IF(U4="",F4-V4,U4+F4-V4)) -> -20000 | X4: 0 | Y4: =IF(F4="","",IF(W4="",F4-X4,W4+F4-X4)) -> -12000 | Z4: 0 | AA4: =IF(F4="","",IF(Y4="",F4-Z4,Y4+F4-Z4)) -> -4000 | AB4: 4000 | AC4: =IF(F4="","",IF(AA4="",F4-AB4,AA4+F4-AB4)) -> 0 | AD4: 8000 | AE4: =IF(F4="","",IF(AC4="",F4-AD4,AC4+F4-AD4)) -> 0 | AF4: 8000 | AG4: =IF(F4="","",IF(AE4="",F4-AF4,AE4+F4-AF4)) -> 0 | AI4: =IF(F4="","",J4+L4+N4+P4+R4+T4+V4+X4+Z4+AB4+AD4+AF4) -> 96000 | AJ4: =IF(F4="","",F4*12) -> 96000 | AK4: =IF(F4="","",AG4) -> 0 | AL4: =IF(F4="","",IF(AK4<=0,"Paid Up",IF(AK4<F4,"Partial","Unpaid"))) -> Paid Up
A5: House 3 | B5: KELVIN | C5: 722616198 | D5: 111 | E5: 1 Bedroom | F5: 8000 | G5: 8000 | J5: 32000 | K5: =IF(F5="","",F5-J5) -> -24000 | L5: 0 | M5: =IF(F5="","",IF(K5="",F5-L5,K5+F5-L5)) -> -16000 | N5: 0 | O5: =IF(F5="","",IF(M5="",F5-N5,M5+F5-N5)) -> -8000 | P5: 0 | Q5: =IF(F5="","",IF(O5="",F5-P5,O5+F5-P5)) -> 0 | R5: 0 | S5: =IF(F5="","",IF(Q5="",F5-R5,Q5+F5-R5)) -> 8000 | T5: 0 | U5: =IF(F5="","",IF(S5="",F5-T5,S5+F5-T5)) -> 16000 | V5: 0 | W5: =IF(F5="","",IF(U5="",F5-V5,U5+F5-V5)) -> 24000 | X5: 0 | Y5: =IF(F5="","",IF(W5="",F5-X5,W5+F5-X5)) -> 32000 | Z5: 0 | AA5: =IF(F5="","",IF(Y5="",F5-Z5,Y5+F5-Z5)) -> 40000 | AB5: 0 | AC5: =IF(F5="","",IF(AA5="",F5-AB5,AA5+F5-AB5)) -> 48000 | AD5: 0 | AE5: =IF(F5="","",IF(AC5="",F5-AD5,AC5+F5-AD5)) -> 56000 | AF5: 13000 | AG5: =IF(F5="","",IF(AE5="",F5-AF5,AE5+F5-AF5)) -> 51000 | AI5: =IF(F5="","",J5+L5+N5+P5+R5+T5+V5+X5+Z5+AB5+AD5+AF5) -> 45000 | AJ5: =IF(F5="","",F5*12) -> 96000 | AK5: =IF(F5="","",AG5) -> 51000 | AL5: =IF(F5="","",IF(AK5<=0,"Paid Up",IF(AK5<F5,"Partial","Unpaid"))) -> Unpaid
A6: House 4 | B6: JOHN | C6: 741582890 | D6: 222 | E6: 1 Bedroom | F6: 8000 | G6: 8000 | J6: 90000 | K6: =IF(F6="","",F6-J6) -> -82000 | L6: 0 | M6: =IF(F6="","",IF(K6="",F6-L6,K6+F6-L6)) -> -74000 | N6: 0 | O6: =IF(F6="","",IF(M6="",F6-N6,M6+F6-N6)) -> -66000 | P6: 0 | Q6: =IF(F6="","",IF(O6="",F6-P6,O6+F6-P6)) -> -58000 | R6: 0 | S6: =IF(F6="","",IF(Q6="",F6-R6,Q6+F6-R6)) -> -50000 | T6: 0 | U6: =IF(F6="","",IF(S6="",F6-T6,S6+F6-T6)) -> -42000 | V6: 0 | W6: =IF(F6="","",IF(U6="",F6-V6,U6+F6-V6)) -> -34000 | X6: 0 | Y6: =IF(F6="","",IF(W6="",F6-X6,W6+F6-X6)) -> -26000 | Z6: 0 | AA6: =IF(F6="","",IF(Y6="",F6-Z6,Y6+F6-Z6)) -> -18000 | AB6: 0 | AC6: =IF(F6="","",IF(AA6="",F6-AB6,AA6+F6-AB6)) -> -10000 | AD6: 0 | AE6: =IF(F6="","",IF(AC6="",F6-AD6,AC6+F6-AD6)) -> -2000 | AF6: 7000 | AG6: =IF(F6="","",IF(AE6="",F6-AF6,AE6+F6-AF6)) -> -1000 | AI6: =IF(F6="","",J6+L6+N6+P6+R6+T6+V6+X6+Z6+AB6+AD6+AF6) -> 97000 | AJ6: =IF(F6="","",F6*12) -> 96000 | AK6: =IF(F6="","",AG6) -> -1000 | AL6: =IF(F6="","",IF(AK6<=0,"Paid Up",IF(AK6<F6,"Partial","Unpaid"))) -> Paid Up
A7: House 5 | B7: VACANT | E7: 1 Bedroom | K7: =IF(F7="","",F7-J7) | M7: =IF(F7="","",IF(K7="",F7-L7,K7+F7-L7)) | O7: =IF(F7="","",IF(M7="",F7-N7,M7+F7-N7)) | Q7: =IF(F7="","",IF(O7="",F7-P7,O7+F7-P7)) | S7: =IF(F7="","",IF(Q7="",F7-R7,Q7+F7-R7)) | U7: =IF(F7="","",IF(S7="",F7-T7,S7+F7-T7)) | W7: =IF(F7="","",IF(U7="",F7-V7,U7+F7-V7)) | Y7: =IF(F7="","",IF(W7="",F7-X7,W7+F7-X7)) | AA7: =IF(F7="","",IF(Y7="",F7-Z7,Y7+F7-Z7)) | AC7: =IF(F7="","",IF(AA7="",F7-AB7,AA7+F7-AB7)) | AE7: =IF(F7="","",IF(AC7="",F7-AD7,AC7+F7-AD7)) | AG7: =IF(F7="","",IF(AE7="",F7-AF7,AE7+F7-AF7)) | AI7: =IF(F7="","",J7+L7+N7+P7+R7+T7+V7+X7+Z7+AB7+AD7+AF7) | AJ7: =IF(F7="","",F7*12) | AK7: =IF(F7="","",AG7) | AL7: =IF(F7="","",IF(AK7<=0,"Paid Up",IF(AK7<F7,"Partial","Unpaid")))
A8: House 6 | B8: VACANT | E8: 1 Bedroom | K8: =IF(F8="","",F8-J8) | M8: =IF(F8="","",IF(K8="",F8-L8,K8+F8-L8)) | O8: =IF(F8="","",IF(M8="",F8-N8,M8+F8-N8)) | Q8: =IF(F8="","",IF(O8="",F8-P8,O8+F8-P8)) | S8: =IF(F8="","",IF(Q8="",F8-R8,Q8+F8-R8)) | U8: =IF(F8="","",IF(S8="",F8-T8,S8+F8-T8)) | W8: =IF(F8="","",IF(U8="",F8-V8,U8+F8-V8)) | Y8: =IF(F8="","",IF(W8="",F8-X8,W8+F8-X8)) | AA8: =IF(F8="","",IF(Y8="",F8-Z8,Y8+F8-Z8)) | AC8: =IF(F8="","",IF(AA8="",F8-AB8,AA8+F8-AB8)) | AE8: =IF(F8="","",IF(AC8="",F8-AD8,AC8+F8-AD8)) | AG8: =IF(F8="","",IF(AE8="",F8-AF8,AE8+F8-AF8)) | AI8: =IF(F8="","",J8+L8+N8+P8+R8+T8+V8+X8+Z8+AB8+AD8+AF8) | AJ8: =IF(F8="","",F8*12) | AK8: =IF(F8="","",AG8) | AL8: =IF(F8="","",IF(AK8<=0,"Paid Up",IF(AK8<F8,"Partial","Unpaid")))
A9: House 7 | B9: VACANT | E9: Bedsitter | K9: =IF(F9="","",F9-J9) | M9: =IF(F9="","",IF(K9="",F9-L9,K9+F9-L9)) | O9: =IF(F9="","",IF(M9="",F9-N9,M9+F9-N9)) | Q9: =IF(F9="","",IF(O9="",F9-P9,O9+F9-P9)) | S9: =IF(F9="","",IF(Q9="",F9-R9,Q9+F9-R9)) | U9: =IF(F9="","",IF(S9="",F9-T9,S9+F9-T9)) | W9: =IF(F9="","",IF(U9="",F9-V9,U9+F9-V9)) | Y9: =IF(F9="","",IF(W9="",F9-X9,W9+F9-X9)) | AA9: =IF(F9="","",IF(Y9="",F9-Z9,Y9+F9-Z9)) | AC9: =IF(F9="","",IF(AA9="",F9-AB9,AA9+F9-AB9)) | AE9: =IF(F9="","",IF(AC9="",F9-AD9,AC9+F9-AD9)) | AG9: =IF(F9="","",IF(AE9="",F9-AF9,AE9+F9-AF9)) | AI9: =IF(F9="","",J9+L9+N9+P9+R9+T9+V9+X9+Z9+AB9+AD9+AF9) | AJ9: =IF(F9="","",F9*12) | AK9: =IF(F9="","",AG9) | AL9: =IF(F9="","",IF(AK9<=0,"Paid Up",IF(AK9<F9,"Partial","Unpaid")))
A10: House 8 | B10: VACANT | E10: Bedsitter | K10: =IF(F10="","",F10-J10) | M10: =IF(F10="","",IF(K10="",F10-L10,K10+F10-L10)) | O10: =IF(F10="","",IF(M10="",F10-N10,M10+F10-N10)) | Q10: =IF(F10="","",IF(O10="",F10-P10,O10+F10-P10)) | S10: =IF(F10="","",IF(Q10="",F10-R10,Q10+F10-R10)) | U10: =IF(F10="","",IF(S10="",F10-T10,S10+F10-T10)) | W10: =IF(F10="","",IF(U10="",F10-V10,U10+F10-V10)) | Y10: =IF(F10="","",IF(W10="",F10-X10,W10+F10-X10)) | AA10: =IF(F10="","",IF(Y10="",F10-Z10,Y10+F10-Z10)) | AC10: =IF(F10="","",IF(AA10="",F10-AB10,AA10+F10-AB10)) | AE10: =IF(F10="","",IF(AC10="",F10-AD10,AC10+F10-AD10)) | AG10: =IF(F10="","",IF(AE10="",F10-AF10,AE10+F10-AF10)) | AI10: =IF(F10="","",J10+L10+N10+P10+R10+T10+V10+X10+Z10+AB10+AD10+AF10) | AJ10: =IF(F10="","",F10*12) | AK10: =IF(F10="","",AG10) | AL10: =IF(F10="","",IF(AK10<=0,"Paid Up",IF(AK10<F10,"Partial","Unpaid")))
A11: House 9 | B11: VACANT | E11: Bedsitter | AL11: VACANT
A12: House 10 | B12: VACANT | E12: Bedsitter | K12: =IF(F12="","",F12-J12) | M12: =IF(F12="","",IF(K12="",F12-L12,K12+F12-L12)) | O12: =IF(F12="","",IF(M12="",F12-N12,M12+F12-N12)) | Q12: =IF(F12="","",IF(O12="",F12-P12,O12+F12-P12)) | S12: =IF(F12="","",IF(Q12="",F12-R12,Q12+F12-R12)) | U12: =IF(F12="","",IF(S12="",F12-T12,S12+F12-T12)) | W12: =IF(F12="","",IF(U12="",F12-V12,U12+F12-V12)) | Y12: =IF(F12="","",IF(W12="",F12-X12,W12+F12-X12)) | AA12: =IF(F12="","",IF(Y12="",F12-Z12,Y12+F12-Z12)) | AC12: =IF(F12="","",IF(AA12="",F12-AB12,AA12+F12-AB12)) | AE12: =IF(F12="","",IF(AC12="",F12-AD12,AC12+F12-AD12)) | AG12: =IF(F12="","",IF(AE12="",F12-AF12,AE12+F12-AF12)) | AI12: =IF(F12="","",J12+L12+N12+P12+R12+T12+V12+X12+Z12+AB12+AD12+AF12) | AJ12: =IF(F12="","",F12*12) | AK12: =IF(F12="","",AG12) | AL12: =IF(F12="","",IF(AK12<=0,"Paid Up",IF(AK12<F12,"Partial","Unpaid")))
A13: House 11 | B13: VACANT | E13: Bedsitter | K13: =IF(F13="","",F13-J13) | M13: =IF(F13="","",IF(K13="",F13-L13,K13+F13-L13)) | O13: =IF(F13="","",IF(M13="",F13-N13,M13+F13-N13)) | Q13: =IF(F13="","",IF(O13="",F13-P13,O13+F13-P13)) | S13: =IF(F13="","",IF(Q13="",F13-R13,Q13+F13-R13)) | U13: =IF(F13="","",IF(S13="",F13-T13,S13+F13-T13)) | W13: =IF(F13="","",IF(U13="",F13-V13,U13+F13-V13)) | Y13: =IF(F13="","",IF(W13="",F13-X13,W13+F13-X13)) | AA13: =IF(F13="","",IF(Y13="",F13-Z13,Y13+F13-Z13)) | AC13: =IF(F13="","",IF(AA13="",F13-AB13,AA13+F13-AB13)) | AE13: =IF(F13="","",IF(AC13="",F13-AD13,AC13+F13-AD13)) | AG13: =IF(F13="","",IF(AE13="",F13-AF13,AE13+F13-AF13)) | AI13: =IF(F13="","",J13+L13+N13+P13+R13+T13+V13+X13+Z13+AB13+AD13+AF13) | AJ13: =IF(F13="","",F13*12) | AK13: =IF(F13="","",AG13) | AL13: =IF(F13="","",IF(AK13<=0,"Paid Up",IF(AK13<F13,"Partial","Unpaid")))
A14: House 12 | B14: VACANT | E14: Bedsitter | AL14: VACANT
A15: House 13 | B15: VACANT | E15: Bedsitter | AL15: VACANT
A16: House 14 | B16: VACANT | E16: Bedsitter | K16: =IF(F16="","",F16-J16) | M16: =IF(F16="","",IF(K16="",F16-L16,K16+F16-L16)) | O16: =IF(F16="","",IF(M16="",F16-N16,M16+F16-N16)) | Q16: =IF(F16="","",IF(O16="",F16-P16,O16+F16-P16)) | S16: =IF(F16="","",IF(Q16="",F16-R16,Q16+F16-R16)) | U16: =IF(F16="","",IF(S16="",F16-T16,S16+F16-T16)) | W16: =IF(F16="","",IF(U16="",F16-V16,U16+F16-V16)) | Y16: =IF(F16="","",IF(W16="",F16-X16,W16+F16-X16)) | AA16: =IF(F16="","",IF(Y16="",F16-Z16,Y16+F16-Z16)) | AC16: =IF(F16="","",IF(AA16="",F16-AB16,AA16+F16-AB16)) | AE16: =IF(F16="","",IF(AC16="",F16-AD16,AC16+F16-AD16)) | AG16: =IF(F16="","",IF(AE16="",F16-AF16,AE16+F16-AF16)) | AI16: =IF(F16="","",J16+L16+N16+P16+R16+T16+V16+X16+Z16+AB16+AD16+AF16) | AJ16: =IF(F16="","",F16*12) | AK16: =IF(F16="","",AG16) | AL16: =IF(F16="","",IF(AK16<=0,"Paid Up",IF(AK16<F16,"Partial","Unpaid")))
F17: 0
F18: 0
F19: 0
F20: 0
F21: 0
F22: 0
F23: 0
F24: 0
F25: 0
F26: 0
F27: 0
F28: 0
... F32: 0
A34: TOTALS | F34: =SUM(F3:F32) -> 31000 | J34: =SUM(J3:J32) -> 179000 | L34: =SUM(L3:L32) -> 7000 | N34: =SUM(N3:N32) -> 7000 | P34: =SUM(P3:P32) -> 0 | R34: =SUM(R3:R32) -> 14000 | T34: =SUM(T3:T32) -> 14000 | V34: =SUM(V3:V32) -> 26000 | X34: =SUM(X3:X32) -> 7000 | Z34: =SUM(Z3:Z32) -> 0 | AB34: =SUM(AB3:AB32) -> 19000 | AD34: =SUM(AD3:AD32) -> 14000 | AF34: =SUM(AF3:AF32) -> 35000 | AI34: =SUM(AI3:AI32) -> 322000 | AK34: =SUM(AK3:AK32) -> 50000
A36: COLOUR KEY: | J36: BLUE = type paid amount here | O36: GREEN balance = paid / credit | U36: RED balance = still owes | AA36: BLUE balance = advance/credit

Sheet Arrears
A1: 🚨 ARREARS SUMMARY — Pulls automatically from Rent Tracker. Fill Action & Last Contact only.
A2: House | B2: Tenant | C2: Rent/Mo | D2: Jan Bal | E2: Feb Bal | F2: Mar Bal | G2: Total Paid YTD | H2: Still Owes | I2: Months Behind | J2: Last Payment | K2: Last Contact | L2: Action | M2: Notes
A3: ='Rent Tracker'!A3 -> House 1 | B3: ='Rent Tracker'!B3 -> IAN | C3: ='Rent Tracker'!F3 -> 7000 | D3: ='Rent Tracker'!K3 -> 0 | E3: ='Rent Tracker'!M3 -> 0 | F3: ='Rent Tracker'!O3 -> 0 | G3: ='Rent Tracker'!AI3 -> 84000 | H3: ='Rent Tracker'!AK3 -> 0 | I3: =IF(OR('Rent Tracker'!F3=0,'Rent Tracker'!F3=""),"", IF('Rent Tracker'!AK3<=0,0, ROUNDUP('Rent Tracker'!AK3/'Rent Tracker'!F3,0))) -> 0 | L3: Legal
A4: ='Rent Tracker'!A4 -> House 2 | B4: ='Rent Tracker'!B4 -> JAMES | C4: ='Rent Tracker'!F4 -> 8000 | D4: ='Rent Tracker'!K4 -> -42000 | E4: ='Rent Tracker'!M4 -> -34000 | F4: ='Rent Tracker'!O4 -> -26000 | G4: ='Rent Tracker'!AI4 -> 96000 | H4: ='Rent Tracker'!AK4 -> 0 | I4: =IF(OR('Rent Tracker'!F4=0,'Rent Tracker'!F4=""),"", IF('Rent Tracker'!AK4<=0,0, ROUNDUP('Rent Tracker'!AK4/'Rent Tracker'!F4,0))) -> 0 | L4: Legal
A5: ='Rent Tracker'!A5 -> House 3 | B5: ='Rent Tracker'!B5 -> KELVIN | C5: ='Rent Tracker'!F5 -> 8000 | D5: ='Rent Tracker'!K5 -> -24000 | E5: ='Rent Tracker'!M5 -> -16000 | F5: ='Rent Tracker'!O5 -> -8000 | G5: ='Rent Tracker'!AI5 -> 45000 | H5: ='Rent Tracker'!AK5 -> 51000 | I5: =IF(OR('Rent Tracker'!F5=0,'Rent Tracker'!F5=""),"", IF('Rent Tracker'!AK5<=0,0, ROUNDUP('Rent Tracker'!AK5/'Rent Tracker'!F5,0))) -> 7 | L5: Notice Issued
A6: ='Rent Tracker'!A6 -> House 4 | B6: ='Rent Tracker'!B6 -> JOHN | C6: ='Rent Tracker'!F6 -> 8000 | D6: ='Rent Tracker'!K6 -> -82000 | E6: ='Rent Tracker'!M6 -> -74000 | F6: ='Rent Tracker'!O6 -> -66000 | G6: ='Rent Tracker'!AI6 -> 97000 | H6: ='Rent Tracker'!AK6 -> -1000 | I6: =IF(OR('Rent Tracker'!F6=0,'Rent Tracker'!F6=""),"", IF('Rent Tracker'!AK6<=0,0, ROUNDUP('Rent Tracker'!AK6/'Rent Tracker'!F6,0))) -> 0 | L6: Pending
A7: ='Rent Tracker'!A7 -> House 5 | B7: ='Rent Tracker'!B7 -> VACANT | C7: ='Rent Tracker'!F7 -> 0 | D7: ='Rent Tracker'!K7 | E7: ='Rent Tracker'!M7 | F7: ='Rent Tracker'!O7 | G7: ='Rent Tracker'!AI7 | H7: ='Rent Tracker'!AK7 | I7: =IF(OR('Rent Tracker'!F7=0,'Rent Tracker'!F7=""),"", IF('Rent Tracker'!AK7<=0,0, ROUNDUP('Rent Tracker'!AK7/'Rent Tracker'!F7,0)))
A8: ='Rent Tracker'!A8 -> House 6 | B8: ='Rent Tracker'!B8 -> VACANT | C8: ='Rent Tracker'!F8 -> 0 | D8: ='Rent Tracker'!K8 | E8: ='Rent Tracker'!M8 | F8: ='Rent Tracker'!O8 | G8: ='Rent Tracker'!AI8 | H8: ='Rent Tracker'!AK8 | I8: =IF(OR('Rent Tracker'!F8=0,'Rent Tracker'!F8=""),"", IF('Rent Tracker'!AK8<=0,0, ROUNDUP('Rent Tracker'!AK8/'Rent Tracker'!F8,0)))
A9: ='Rent Tracker'!A9 -> House 7 | B9: ='Rent Tracker'!B9 -> VACANT | C9: ='Rent Tracker'!F9 -> 0 | D9: ='Rent Tracker'!K9 | E9: ='Rent Tracker'!M9 | F9: ='Rent Tracker'!O9 | G9: ='Rent Tracker'!AI9 | H9: ='Rent Tracker'!AK9 | I9: =IF(OR('Rent Tracker'!F9=0,'Rent Tracker'!F9=""),"", IF('Rent Tracker'!AK9<=0,0, ROUNDUP('Rent Tracker'!AK9/'Rent Tracker'!F9,0)))
A10: ='Rent Tracker'!A10 -> House 8 | B10: ='Rent Tracker'!B10 -> VACANT | C10: ='Rent Tracker'!F10 -> 0 | D10: ='Rent Tracker'!K10 | E10: ='Rent Tracker'!M10 | F10: ='Rent Tracker'!O10 | G10: ='Rent Tracker'!AI10 | H10: ='Rent Tracker'!AK10 | I10: =IF(OR('Rent Tracker'!F10=0,'Rent Tracker'!F10=""),"", IF('Rent Tracker'!AK10<=0,0, ROUNDUP('Rent Tracker'!AK10/'Rent Tracker'!F10,0)))
A11: ='Rent Tracker'!A11 -> House 9 | B11: ='Rent Tracker'!B11 -> VACANT | C11: ='Rent Tracker'!F11 -> 0 | D11: ='Rent Tracker'!K11 -> 0 | E11: ='Rent Tracker'!M11 -> 0 | F11: ='Rent Tracker'!O11 -> 0 | G11: ='Rent Tracker'!AI11 -> 0 | H11: ='Rent Tracker'!AK11 -> 0 | I11: =IF(OR('Rent Tracker'!F11=0,'Rent Tracker'!F11=""),"", IF('Rent Tracker'!AK11<=0,0, ROUNDUP('Rent Tracker'!AK11/'Rent Tracker'!F11,0)))
A12: ='Rent Tracker'!A12 -> House 10 | B12: ='Rent Tracker'!B12 -> VACANT | C12: ='Rent Tracker'!F12 -> 0 | D12: ='Rent Tracker'!K12 | E12: ='Rent Tracker'!M12 | F12: ='Rent Tracker'!O12 | G12: ='Rent Tracker'!AI12 | H12: ='Rent Tracker'!AK12 | I12: =IF(OR('Rent Tracker'!F12=0,'Rent Tracker'!F12=""),"", IF('Rent Tracker'!AK12<=0,0, ROUNDUP('Rent Tracker'!AK12/'Rent Tracker'!F12,0)))
A13: ='Rent Tracker'!A13 -> House 11 | B13: ='Rent Tracker'!B13 -> VACANT | C13: ='Rent Tracker'!F13 -> 0 | D13: ='Rent Tracker'!K13 | E13: ='Rent Tracker'!M13 | F13: ='Rent Tracker'!O13 | G13: ='Rent Tracker'!AI13 | H13: ='Rent Tracker'!AK13 | I13: =IF(OR('Rent Tracker'!F13=0,'Rent Tracker'!F13=""),"", IF('Rent Tracker'!AK13<=0,0, ROUNDUP('Rent Tracker'!AK13/'Rent Tracker'!F13,0)))
A14: ='Rent Tracker'!A14 -> House 12 | B14: ='Rent Tracker'!B14 -> VACANT | C14: ='Rent Tracker'!F14 -> 0 | D14: ='Rent Tracker'!K14 -> 0 | E14: ='Rent Tracker'!M14 -> 0 | F14: ='Rent Tracker'!O14 -> 0 | G14: ='Rent Tracker'!AI14 -> 0 | H14: ='Rent Tracker'!AK14 -> 0 | I14: =IF(OR('Rent Tracker'!F14=0,'Rent Tracker'!F14=""),"", IF('Rent Tracker'!AK14<=0,0, ROUNDUP('Rent Tracker'!AK14/'Rent Tracker'!F14,0)))
A15: ='Rent Tracker'!A15 -> House 13 | B15: ='Rent Tracker'!B15 -> VACANT | C15: ='Rent Tracker'!F15 -> 0 | D15: ='Rent Tracker'!K15 -> 0 | E15: ='Rent Tracker'!M15 -> 0 | F15: ='Rent Tracker'!O15 -> 0 | G15: ='Rent Tracker'!AI15 -> 0 | H15: ='Rent Tracker'!AK15 -> 0 | I15: =IF(OR('Rent Tracker'!F15=0,'Rent Tracker'!F15=""),"", IF('Rent Tracker'!AK15<=0,0, ROUNDUP('Rent Tracker'!AK15/'Rent Tracker'!F15,0)))
A16: ='Rent Tracker'!A16 -> House 14 | B16: ='Rent Tracker'!B16 -> VACANT | C16: ='Rent Tracker'!F16 -> 0 | D16: ='Rent Tracker'!K16 | E16: ='Rent Tracker'!M16 | F16: ='Rent Tracker'!O16 | G16: ='Rent Tracker'!AI16 | H16: ='Rent Tracker'!AK16 | I16: =IF(OR('Rent Tracker'!F16=0,'Rent Tracker'!F16=""),"", IF('Rent Tracker'!AK16<=0,0, ROUNDUP('Rent Tracker'!AK16/'Rent Tracker'!F16,0)))
A17: ='Rent Tracker'!A17 -> 0 | B17: ='Rent Tracker'!B17 -> 0 | C17: ='Rent Tracker'!F17 -> 0 | D17: ='Rent Tracker'!K17 -> 0 | E17: ='Rent Tracker'!M17 -> 0 | F17: ='Rent Tracker'!O17 -> 0 | G17: ='Rent Tracker'!AI17 -> 0 | H17: ='Rent Tracker'!AK17 -> 0 | I17: =IF(OR('Rent Tracker'!F17=0,'Rent Tracker'!F17=""),"", IF('Rent Tracker'!AK17<=0,0, ROUNDUP('Rent Tracker'!AK17/'Rent Tracker'!F17,0)))
A18: ='Rent Tracker'!A18 -> 0 | B18: ='Rent Tracker'!B18 -> 0 | C18: ='Rent Tracker'!F18 -> 0 | D18: ='Rent Tracker'!K18 -> 0 | E18: ='Rent Tracker'!M18 -> 0 | F18: ='Rent Tracker'!O18 -> 0 | G18: ='Rent Tracker'!AI18 -> 0 | H18: ='Rent Tracker'!AK18 -> 0 | I18: =IF(OR('Rent Tracker'!F18=0,'Rent Tracker'!F18=""),"", IF('Rent Tracker'!AK18<=0,0, ROUNDUP('Rent Tracker'!AK18/'Rent Tracker'!F18,0)))
... A32: ='Rent Tracker'!A32 -> 0 | B32: ='Rent Tracker'!B32 -> 0 | C32: ='Rent Tracker'!F32 -> 0 | D32: ='Rent Tracker'!K32 -> 0 | E32: ='Rent Tracker'!M32 -> 0 | F32: ='Rent Tracker'!O32 -> 0 | G32: ='Rent Tracker'!AI32 -> 0 | H32: ='Rent Tracker'!AK32 -> 0 | I32: =IF(OR('Rent Tracker'!F32=0,'Rent Tracker'!F32=""),"", IF('Rent Tracker'!AK32<=0,0, ROUNDUP('Rent Tracker'!AK32/'Rent Tracker'!F32,0)))
A34: TOTALS | G34: =SUM(G3:G32) -> 322000 | H34: =SUM(H3:H32) -> 50000

Sheet Deposits
A1: 💎 DEPOSITS REGISTER — Security deposits held, deductions on move-out, net refundable.
A2: House | B2: Tenant | C2: Deposit Held (KSh) | D2: Date Received | E2: Deduction 1 Reason | F2: Deduction 1 (KSh) | G2: Deduction 2 Reason | H2: Deduction 2 (KSh) | I2: Total Deductions | J2: Net Refundable | K2: Date Refunded | L2: Status
A3: House 1 | B3: James Nderitu | C3: 7000 | I3: =IF(AND(F3="",H3=""),"",IF(F3="",0,F3)+IF(H3="",0,H3)) | J3: =IF(C3="","",C3-IF(I3="",0,I3)) -> 7000 | L3: Held
A4: House 2 | B4: Ian Gichuru | C4: 8000 | I4: =IF(AND(F4="",H4=""),"",IF(F4="",0,F4)+IF(H4="",0,H4)) | J4: =IF(C4="","",C4-IF(I4="",0,I4)) -> 8000 | L4: Held
A5: House 3 | B5: Joshua | C5: 8000 | I5: =IF(AND(F5="",H5=""),"",IF(F5="",0,F5)+IF(H5="",0,H5)) | J5: =IF(C5="","",C5-IF(I5="",0,I5)) -> 8000 | L5: Held
A6: House 4 | B6: Kelvin | C6: 8000 | I6: =IF(AND(F6="",H6=""),"",IF(F6="",0,F6)+IF(H6="",0,H6)) | J6: =IF(C6="","",C6-IF(I6="",0,I6)) -> 8000 | L6: Held
A7: House 5 | B7: Joan | C7: 8000 | I7: =IF(AND(F7="",H7=""),"",IF(F7="",0,F7)+IF(H7="",0,H7)) | J7: =IF(C7="","",C7-IF(I7="",0,I7)) -> 8000 | L7: Held
A8: House 6 | B8: Brian | C8: 8000 | I8: =IF(AND(F8="",H8=""),"",IF(F8="",0,F8)+IF(H8="",0,H8)) | J8: =IF(C8="","",C8-IF(I8="",0,I8)) -> 8000 | L8: Held
A9: House 7 | B9: Kare | C9: 5500 | I9: =IF(AND(F9="",H9=""),"",IF(F9="",0,F9)+IF(H9="",0,H9)) | J9: =IF(C9="","",C9-IF(I9="",0,I9)) -> 5500 | L9: Held
A10: House 8 | B10: John | C10: 5500 | I10: =IF(AND(F10="",H10=""),"",IF(F10="",0,F10)+IF(H10="",0,H10)) | J10: =IF(C10="","",C10-IF(I10="",0,I10)) -> 5500 | L10: Held
I11: =IF(AND(F11="",H11=""),"",IF(F11="",0,F11)+IF(H11="",0,H11)) | J11: =IF(C11="","",C11-IF(I11="",0,I11))
A12: House 10 | B12: Korir | C12: 5500 | I12: =IF(AND(F12="",H12=""),"",IF(F12="",0,F12)+IF(H12="",0,H12)) | J12: =IF(C12="","",C12-IF(I12="",0,I12)) -> 5500 | L12: Held
A13: House 11 | B13: Cheptegei | C13: 5500 | I13: =IF(AND(F13="",H13=""),"",IF(F13="",0,F13)+IF(H13="",0,H13)) | J13: =IF(C13="","",C13-IF(I13="",0,I13)) -> 5500 | L13: Held
I14: =IF(AND(F14="",H14=""),"",IF(F14="",0,F14)+IF(H14="",0,H14)) | J14: =IF(C14="","",C14-IF(I14="",0,I14))
I15: =IF(AND(F15="",H15=""),"",IF(F15="",0,F15)+IF(H15="",0,H15)) | J15: =IF(C15="","",C15-IF(I15="",0,I15))
A16: House 14 | B16: Burudi | C16: 5500 | I16: =IF(AND(F16="",H16=""),"",IF(F16="",0,F16)+IF(H16="",0,H16)) | J16: =IF(C16="","",C16-IF(I16="",0,I16)) -> 5500 | L16: Held
I17: =IF(AND(F17="",H17=""),"",IF(F17="",0,F17)+IF(H17="",0,H17)) | J17: =IF(C17="","",C17-IF(I17="",0,I17)) | L17: Held
I18: =IF(AND(F18="",H18=""),"",IF(F18="",0,F18)+IF(H18="",0,H18)) | J18: =IF(C18="","",C18-IF(I18="",0,I18)) | L18: Held
I19: =IF(AND(F19="",H19=""),"",IF(F19="",0,F19)+IF(H19="",0,H19)) | J19: =IF(C19="","",C19-IF(I19="",0,I19)) | L19: Held
I20: =IF(AND(F20="",H20=""),"",IF(F20="",0,F20)+IF(H20="",0,H20)) | J20: =IF(C20="","",C20-IF(I20="",0,I20)) | L20: Held
I21: =IF(AND(F21="",H21=""),"",IF(F21="",0,F21)+IF(H21="",0,H21)) | J21: =IF(C21="","",C21-IF(I21="",0,I21)) | L21: Held
I22: =IF(AND(F22="",H22=""),"",IF(F22="",0,F22)+IF(H22="",0,H22)) | J22: =IF(C22="","",C22-IF(I22="",0,I22)) | L22: Held
I23: =IF(AND(F23="",H23=""),"",IF(F23="",0,F23)+IF(H23="",0,H23)) | J23: =IF(C23="","",C23-IF(I23="",0,I23)) | L23: Held
I24: =IF(AND(F24="",H24=""),"",IF(F24="",0,F24)+IF(H24="",0,H24)) | J24: =IF(C24="","",C24-IF(I24="",0,I24)) | L24: Held
I25: =IF(AND(F25="",H25=""),"",IF(F25="",0,F25)+IF(H25="",0,H25)) | J25: =IF(C25="","",C25-IF(I25="",0,I25)) | L25: Held
I26: =IF(AND(F26="",H26=""),"",IF(F26="",0,F26)+IF(H26="",0,H26)) | J26: =IF(C26="","",C26-IF(I26="",0,I26)) | L26: Held
I27: =IF(AND(F27="",H27=""),"",IF(F27="",0,F27)+IF(H27="",0,H27)) | J27: =IF(C27="","",C27-IF(I27="",0,I27)) | L27: Held
I28: =IF(AND(F28="",H28=""),"",IF(F28="",0,F28)+IF(H28="",0,H28)) | J28: =IF(C28="","",C28-IF(I28="",0,I28)) | L28: Held
... I32: =IF(AND(F32="",H32=""),"",IF(F32="",0,F32)+IF(H32="",0,H32)) | J32: =IF(C32="","",C32-IF(I32="",0,I32)) | L32: Held

Sheet Maintenance
A1: 🔧 MAINTENANCE LOG — Every repair, cost and contractor tracked here.
A2: # | B2: Date | C2: House No. | D2: Issue Description | E2: Category | F2: Priority | G2: Contractor | H2: Date Done | I2: Cost (KSh) | J2: Paid? | K2: Charged to Tenant? | L2: Status | M2: Month | N2: Notes
A3: 1 | C3: 1 | E3: Painting | F3: High | I3: 2000 | J3: Yes | K3: Yes | L3: In Progress | M3: Mar
A4: =IF(B4="","",ROW()-2)
A5: =IF(B5="","",ROW()-2)
A6: =IF(B6="","",ROW()-2)
A7: =IF(B7="","",ROW()-2)
A8: =IF(B8="","",ROW()-2)
A9: =IF(B9="","",ROW()-2)
A10: =IF(B10="","",ROW()-2)
A11: =IF(B11="","",ROW()-2)
A12: =IF(B12="","",ROW()-2)
A13: =IF(B13="","",ROW()-2)
A14: =IF(B14="","",ROW()-2)
A15: =IF(B15="","",ROW()-2)
... A502: =IF(B502="","",ROW()-2)

Sheet Expenses
A1: 💸 EXPENSES 2026 — Type actual spend in each month. Blue = input. Totals auto-calculate.
A2: Expense Category | B2: Type | C2: Annual Budget (KSh) | D2: Jan | E2: Feb | F2: Mar | G2: Apr | H2: May | I2: Jun | J2: Jul | K2: Aug | L2: Sep | M2: Oct | N2: Nov | O2: Dec | P2: Total Spent | Q2: Annual Budget | R2: vs Budget
A3: Mortgage / Loan Repayment | B3: Fixed | P3: =SUM(D3:O3) -> 0 | Q3: =C3 -> 0 | R3: =IF(C3=0,"",P3-C3)
A4: Property Rates & Levies | B4: Fixed | P4: =SUM(D4:O4) -> 0 | Q4: =C4 -> 0 | R4: =IF(C4=0,"",P4-C4)
A5: Insurance | B5: Fixed | P5: =SUM(D5:O5) -> 0 | Q5: =C5 -> 0 | R5: =IF(C5=0,"",P5-C5)
A6: Caretaker / Manager Salary | B6: Fixed | D6: 5000 | P6: =SUM(D6:O6) -> 5000 | Q6: =C6 -> 0 | R6: =IF(C6=0,"",P6-C6)
A7: Security | B7: Fixed | P7: =SUM(D7:O7) -> 0 | Q7: =C7 -> 0 | R7: =IF(C7=0,"",P7-C7)
A8: Common Area Water | B8: Utility | P8: =SUM(D8:O8) -> 0 | Q8: =C8 -> 0 | R8: =IF(C8=0,"",P8-C8)
A9: Common Area Electricity | B9: Utility | P9: =SUM(D9:O9) -> 0 | Q9: =C9 -> 0 | R9: =IF(C9=0,"",P9-C9)
A10: Garbage Collection | B10: Utility | D10: 1000 | P10: =SUM(D10:O10) -> 1000 | Q10: =C10 -> 0 | R10: =IF(C10=0,"",P10-C10)
A11: Internet / CCTV | B11: Utility | P11: =SUM(D11:O11) -> 0 | Q11: =C11 -> 0 | R11: =IF(C11=0,"",P11-C11)
A12: Plumbing & Repairs | B12: Maintenance | D12: 2000 | P12: =SUM(D12:O12) -> 2000 | Q12: =C12 -> 0 | R12: =IF(C12=0,"",P12-C12)
A13: Electrical Repairs | B13: Maintenance | P13: =SUM(D13:O13) -> 0 | Q13: =C13 -> 0 | R13: =IF(C13=0,"",P13-C13)
A14: Painting & Decoration | B14: Maintenance | P14: =SUM(D14:O14) -> 0 | Q14: =C14 -> 0 | R14: =IF(C14=0,"",P14-C14)
A15: Cleaning & Fumigation | B15: Maintenance | D15: 1000 | P15: =SUM(D15:O15) -> 1000 | Q15: =C15 -> 0 | R15: =IF(C15=0,"",P15-C15)
A16: Structural / Civil Works | B16: Maintenance | P16: =SUM(D16:O16) -> 0 | Q16: =C16 -> 0 | R16: =IF(C16=0,"",P16-C16)
A17: Legal & Professional Fees | B17: Admin | P17: =SUM(D17:O17) -> 0 | Q17: =C17 -> 0 | R17: =IF(C17=0,"",P17-C17)
A18: Advertising / Re-letting | B18: Admin | P18: =SUM(D18:O18) -> 0 | Q18: =C18 -> 0 | R18: =IF(C18=0,"",P18-C18)
A19: Accounting / Bookkeeping | B19: Admin | P19: =SUM(D19:O19) -> 0 | Q19: =C19 -> 0 | R19: =IF(C19=0,"",P19-C19)
A20: Bank Charges | B20: Admin | P20: =SUM(D20:O20) -> 0 | Q20: =C20 -> 0 | R20: =IF(C20=0,"",P20-C20)
A21: Capital Improvement | B21: CapEx | P21: =SUM(D21:O21) -> 0 | Q21: =C21 -> 0 | R21: =IF(C21=0,"",P21-C21)
A22: Miscellaneous / Other | B22: Variable | P22: =SUM(D22:O22) -> 0 | Q22: =C22 -> 0 | R22: =IF(C22=0,"",P22-C22)
A23: TOTAL EXPENSES | C23: =SUM(C3:C22) -> 0 | D23: =SUM(D3:D22) -> 9000 | E23: =SUM(E3:E22) -> 0 | F23: =SUM(F3:F22) -> 0 | G23: =SUM(G3:G22) -> 0 | H23: =SUM(H3:H22) -> 0 | I23: =SUM(I3:I22) -> 0 | J23: =SUM(J3:J22) -> 0 | ... R23: =SUM(R3:R22) -> 0

Sheet P&L Summary
A1: 📈 PROFIT & LOSS 2026 — Fully automatic. Do NOT type here. Reads from Rent Tracker & Expenses.
A2: Line Item | B2: Category | C2: Jan | D2: Feb | E2: Mar | F2: Apr | G2: May | H2: Jun | I2: Jul | J2: Aug | K2: Sep | L2: Oct | M2: Nov | N2: Dec | O2: YTD Total | P2: Annual Budget | Q2: vs Budget
A3: ── INCOME ──
A4: Rent Collected | B4: Income | C4: ='Rent Tracker'!J34 -> 179000 | D4: ='Rent Tracker'!L34 -> 7000 | E4: ='Rent Tracker'!N34 -> 7000 | F4: ='Rent Tracker'!P34 -> 0 | G4: ='Rent Tracker'!R34 -> 14000 | H4: ='Rent Tracker'!T34 -> 14000 | I4: ='Rent Tracker'!V34 -> 26000 | J4: ='Rent Tracker'!X34 -> 7000 | K4: ='Rent Tracker'!Z34 -> 0 | L4: ='Rent Tracker'!AB34 -> 19000 | M4: ='Rent Tracker'!AD34 -> 14000 | N4: ='Rent Tracker'!AF34 -> 35000
A5: Other Income | B5: Income
A6: TOTAL INCOME | B6: Subtotal | O6: =SUM(C6:N6) -> 0
A8: ── EXPENSES ──
A9: Total Expenses | B9: Expense | C9: =Expenses!D23 -> 9000 | D9: =Expenses!E23 -> 0 | E9: =Expenses!F23 -> 0 | F9: =Expenses!G23 -> 0 | G9: =Expenses!H23 -> 0 | H9: =Expenses!I23 -> 0 | I9: =Expenses!J23 -> 0 | J9: =Expenses!K23 -> 0 | ... N9: =Expenses!O23 -> 0
A10: TOTAL EXPENSES | B10: Subtotal | C10: =C8 -> 0 | D10: =D8 -> 0 | E10: =E8 -> 0 | F10: =F8 -> 0 | G10: =G8 -> 0 | H10: =H8 -> 0 | I10: =I8 -> 0 | J10: =J8 -> 0 | ... N10: =N8 -> 0 | O10: =SUM(C10:N10) -> 0
A12: NET PROFIT | B12: Net | C12: =C6-C10 -> 0 | D12: =D6-D10 -> 0 | E12: =E6-E10 -> 0 | F12: =F6-F10 -> 0 | G12: =G6-G10 -> 0 | H12: =H6-H10 -> 0 | I12: =I6-I10 -> 0 | J12: =J6-J10 -> 0 | ... O12: =O6-O10 -> 0
A13: Occupancy Rate | B13: KPI | O13: =IFERROR(COUNTIF('Rent Tracker'!B3:B32,"<>VACANT")/COUNTA('Rent Tracker'!A3:A32),0) -> 1.4285714
A14: Collection Rate | B14: KPI | O14: =IFERROR(AI34/(AJ34),0) -> 0
